tpQtLib/__init__.py
tpQtLib/__version__.py
tpQtLib/core/__init__.py
tpQtLib/core/animation.py
tpQtLib/core/base.py
tpQtLib/core/color.py
tpQtLib/core/dialog.py
tpQtLib/core/icon.py
tpQtLib/core/image.py
tpQtLib/core/menu.py
tpQtLib/core/pixmap.py
tpQtLib/core/qtutils.py
tpQtLib/core/resource.py
tpQtLib/core/settings.py
tpQtLib/core/style.py
tpQtLib/core/svg.py
tpQtLib/core/theme.py
tpQtLib/core/timers.py
tpQtLib/core/traymessage.py
tpQtLib/core/window.py
tpQtLib/core/worker.py
tpQtLib/resources/__init__.py
tpQtLib/resources/__init__.pyc
tpQtLib/resources/res.py
tpQtLib/resources/res.pyc
tpQtLib/resources/res.qrc
tpQtLib/resources/icons/camera.svg
tpQtLib/resources/icons/expand.svg
tpQtLib/resources/icons/folder.svg
tpQtLib/resources/icons/rignode_icon.png
tpQtLib/resources/icons/black/add.png
tpQtLib/resources/icons/black/check_box_checked_black.png
tpQtLib/resources/icons/black/check_box_unchecked_black.png
tpQtLib/resources/icons/black/delete.png
tpQtLib/resources/icons/black/descending_sorting.png
tpQtLib/resources/icons/black/filter.png
tpQtLib/resources/icons/black/folder.png
tpQtLib/resources/icons/black/grid_view.png
tpQtLib/resources/icons/black/open_folder.png
tpQtLib/resources/icons/black/plus.png
tpQtLib/resources/icons/black/radio_button_checked_black.png
tpQtLib/resources/icons/black/radio_button_unchecked_black.png
tpQtLib/resources/icons/black/search.png
tpQtLib/resources/icons/black/settings.png
tpQtLib/resources/icons/black/slider.png
tpQtLib/resources/icons/black/sync.png
tpQtLib/resources/icons/black/trash.png
tpQtLib/resources/icons/black/view_all.png
tpQtLib/resources/icons/black/view_compact.png
tpQtLib/resources/icons/color/add.png
tpQtLib/resources/icons/color/align_bottom.png
tpQtLib/resources/icons/color/align_left.png
tpQtLib/resources/icons/color/align_right.png
tpQtLib/resources/icons/color/align_top.png
tpQtLib/resources/icons/color/arrow_down.png
tpQtLib/resources/icons/color/arrow_left.png
tpqtlib-0.0.6.dist-info/LICENSE
tpqtlib-0.0.6.dist-info/METADATA
tpqtlib-0.0.6.dist-info/WHEEL
tpqtlib-0.0.6.dist-info/top_level.txt
tpqtlib-0.0.6.dist-info/RECORD
