Metadata-Version: 2.1
Name: tpqtlib
Version: 0.0.6
Summary: Collection of Python utilities modules to work with PySide/PyQt and DCCs
Home-page: https://github.com/tpoveda/tpQtLib
Author: Tomas Poveda
Author-email: tpovedatd@gmail.com
License: MIT
Platform: UNKNOWN
Requires-Dist: Qt.py
Requires-Dist: tpPyUtils
Requires-Dist: tpDccLib
Requires-Dist: PySide ; python_version <= "3.4"
Requires-Dist: PySide2 ; python_version > "3.4"
Provides-Extra: dev
Requires-Dist: wheel ; extra == 'dev'
Provides-Extra: test
Requires-Dist: pytest ; extra == 'test'
